LICENSE.md
README.md
setup.py
geo_extractor/__init__.py
geo_extractor/constants.py
geo_extractor/py.typed
geo_extractor/dataformats/__init__.py
geo_extractor/dataformats/datapoint.py
geo_extractor/dataformats/event.py
geo_extractor/dataformats/geojson.py
geo_extractor/downloaders/__init__.py
geo_extractor/downloaders/base.py
geo_extractor/downloaders/bellingcat.py
geo_extractor/downloaders/ceninfores.py
geo_extractor/downloaders/defmon.py
geo_extractor/downloaders/defmon_spreadsheet.py
geo_extractor/downloaders/geoconfirmed.py
geo_extractor/downloaders/reukraine.py
geo_extractor/downloaders/texty.py
geo_extractor/extractors/__init__.py
geo_extractor/extractors/bellingcat.py
geo_extractor/extractors/ceninfores.py
geo_extractor/extractors/defmon.py
geo_extractor/extractors/defmon_spreadsheet.py
geo_extractor/extractors/geoconfirmed.py
geo_extractor/extractors/geoconfirmed_old.py
geo_extractor/extractors/geojson.py
geo_extractor/extractors/reukraine.py
geo_extractor/extractors/texty.py
osint_geo_extractor.egg-info/PKG-INFO
osint_geo_extractor.egg-info/SOURCES.txt
osint_geo_extractor.egg-info/dependency_links.txt
osint_geo_extractor.egg-info/not-zip-safe
osint_geo_extractor.egg-info/top_level.txt
tests/__init__.py
tests/conftest.py
tests/fixtures.py
tests/generate_fixtures.py
tests/generate_geojson.py
tests/test_downloaders.py
tests/test_e2e.py
tests/test_formats.py
tests/test_geojson.py