Metadata-Version: 2.1
Name: osint-geo-extractor
Version: 0.0.12
Summary: Geo-related info extraction library for Bellingcat, Cen4InfoRes etc
Home-page: https://github.com/conflict-investigations/osint-geo-extractor
Author: conflict-investigations
License: MIT
Classifier: Development Status :: 4 - Beta
Classifier: Programming Language :: Python :: 3.9
Classifier: Programming Language :: Python :: 3.10
Classifier: Programming Language :: Python :: 3.11
Classifier: License :: OSI Approved :: MIT License
Requires-Python: >=3.9
License-File: LICENSE.md
